mkpi/__init__.py
mkpi/mkpi.py
mkpi/template/LICENSE.MIT
mkpi/template/README.md
mkpi/template/setup.cfg
mkpi/template/setup.py.tpl
mkpi-0.1.1.dist-info/METADATA
mkpi-0.1.1.dist-info/RECORD
mkpi-0.1.1.dist-info/WHEEL
mkpi-0.1.1.dist-info/entry_points.txt
mkpi-0.1.1.dist-info/top_level.txt
