Metadata-Version: 2.1
Name: mkpi
Version: 0.1.1
Summary: make python project setuptools template
Home-page: https://github.com/wanix1988/python-setup-boilerplate
Author: Linwei Wang
Author-email: wenix@live.cn
License: UNKNOWN
Platform: UNKNOWN
Classifier: Programming Language :: Python :: 3
Classifier: License :: OSI Approved :: MIT License
Classifier: Operating System :: OS Independent
